bayesian_average/__init__.py
bayesian_average/average.py
bayesian_average-0.0.1.dist-info/LICENSE.txt
bayesian_average-0.0.1.dist-info/METADATA
bayesian_average-0.0.1.dist-info/WHEEL
bayesian_average-0.0.1.dist-info/top_level.txt
bayesian_average-0.0.1.dist-info/RECORD
