Metadata-Version: 2.1
Name: bayesian-average
Version: 0.0.1
Summary: Python package to calculate the weighted average with Bayesian methods
Author: Marleen Maxton
License: X11
License-File: LICENSE.txt
